unstructured_inference/__init__.py
unstructured_inference/__version__.py
unstructured_inference/config.py
unstructured_inference/constants.py
unstructured_inference/logger.py
unstructured_inference/math.py
unstructured_inference/utils.py
unstructured_inference/visualize.py
unstructured_inference/inference/__init__.py
unstructured_inference/inference/elements.py
unstructured_inference/inference/layout.py
unstructured_inference/inference/layoutelement.py
unstructured_inference/models/__init__.py
unstructured_inference/models/base.py
unstructured_inference/models/detectron2onnx.py
unstructured_inference/models/eval.py
unstructured_inference/models/table_postprocess.py
unstructured_inference/models/tables.py
unstructured_inference/models/unstructuredmodel.py
unstructured_inference/models/yolox.py
unstructured_inference-1.2.0.dist-info/METADATA
unstructured_inference-1.2.0.dist-info/WHEEL
unstructured_inference-1.2.0.dist-info/top_level.txt
unstructured_inference-1.2.0.dist-info/RECORD
