Metadata-Version: 2.4
Name: unstructured_inference
Version: 1.2.0
Summary: A library for performing inference using trained models.
Home-page: https://github.com/Unstructured-IO/unstructured-inference
Author: Unstructured Technologies
Author-email: devops@unstructuredai.io
License: Apache-2.0
Keywords: NLP PDF HTML CV XML parsing preprocessing
Classifier: Development Status :: 4 - Beta
Classifier: Intended Audience :: Developers
Classifier: Intended Audience :: Education
Classifier: Intended Audience :: Science/Research
Classifier: License :: OSI Approved :: Apache Software License
Classifier: Operating System :: OS Independent
Classifier: Programming Language :: Python :: 3
Classifier: Programming Language :: Python :: 3.8
Classifier: Programming Language :: Python :: 3.9
Classifier: Topic :: Scientific/Engineering :: Artificial Intelligence
Requires-Python: >=3.7.0
Requires-Dist: python-multipart
Requires-Dist: huggingface-hub
Requires-Dist: numpy
Requires-Dist: opencv-python>=4.13.0.90
Requires-Dist: onnx
Requires-Dist: onnxruntime>=1.18.0
Requires-Dist: matplotlib
Requires-Dist: torch
Requires-Dist: timm
Requires-Dist: transformers>=4.25.1
Requires-Dist: accelerate
Requires-Dist: rapidfuzz
Requires-Dist: pandas
Requires-Dist: scipy
Requires-Dist: pypdfium2>=5.0.0
Requires-Dist: pdfminer-six
Dynamic: author
Dynamic: author-email
Dynamic: classifier
Dynamic: description
Dynamic: description-content-type
Dynamic: home-page
Dynamic: keywords
Dynamic: license
Dynamic: requires-dist
Dynamic: requires-python
Dynamic: summary
